{
    "version": "9.19",
    "description": "Video game library manager and launcher with support for 3rd party libraries like Steam, GOG, Epic, Origin, Ubisoft Connect, and more!",
    "homepage": "https://playnite.link",
    "license": "MIT",
    "url": "https://github.com/JosefNemec/Playnite/releases/download/9.19/Playnite919.zip",
    "hash": "17d7499397088ec9e239c874a0f90a1eed699daa17b9344702ee112ff087c270",
    "pre_install": "Copy-Item \"$persist_dir\\config.json\" \"$dir\" -ErrorAction SilentlyContinue",
    "uninstaller": {
        "script": "Copy-Item \"$dir\\config.json\" \"$persist_dir\" -ErrorAction SilentlyContinue -Force"
    },
    "bin": [
        [
            "Playnite.DesktopApp.exe",
            "Playnite"
        ]
    ],
    "shortcuts": [
        [
            "Playnite.DesktopApp.exe",
            "Playnite"
        ]
    ],
    "persist": [
        "browsercache",
        "cache",
        "Extensions",
        "ExtensionsData",
        "Themes",
        "library"
    ],
    "checkver": {
        "github": "https://github.com/JosefNemec/Playnite"
    },
    "autoupdate": {
        "url": "https://github.com/JosefNemec/Playnite/releases/download/$version/Playnite$cleanVersion.zip"
    }
}
